marinilla/__init__.py
marinilla/parque.py
marinilla-0.1.1.dist-info/METADATA
marinilla-0.1.1.dist-info/WHEEL
marinilla-0.1.1.dist-info/top_level.txt
marinilla-0.1.1.dist-info/RECORD
