Metadata-Version: 2.1
Name: marinilla
Version: 0.1.1
Summary: Libreria de suma
Home-page: UNKNOWN
Author: Juan Esteban Ospina 
Author-email: juan.ospina25@udea.edu.co
License: MIT
Platform: UNKNOWN
Requires-Python: >=3.10.12
Requires-Dist: numpy (==1.26.1)
Requires-Dist: pandas (==2.1.1)
